ytmusic_wrapper/__init__.py
ytmusic_wrapper/api_calls.py
ytmusic_wrapper/http_calls.py
ytmusic_wrapper-0.0.5.dist-info/METADATA
ytmusic_wrapper-0.0.5.dist-info/WHEEL
ytmusic_wrapper-0.0.5.dist-info/licenses/LICENSE.md
ytmusic_wrapper-0.0.5.dist-info/RECORD
