Metadata-Version: 2.4
Name: ytmusic-wrapper
Version: 0.0.5
Summary: A Python Library for Home Assistant for the Youtube Music Wrapper API
Author: Zerwin
License:                     GNU AFFERO GENERAL PUBLIC LICENSE
License-File: LICENSE.md
Classifier: License :: OSI Approved :: GNU Affero General Public License v3 or later (AGPLv3+)
Classifier: Operating System :: OS Independent
Classifier: Programming Language :: Python :: 3
Requires-Python: >=3.8
Requires-Dist: aiohttp
